ColorfulEngine/__init__.py
colorfulengine-1.0.2.dist-info/METADATA
colorfulengine-1.0.2.dist-info/WHEEL
colorfulengine-1.0.2.dist-info/licenses/LICENSE
colorfulengine-1.0.2.dist-info/RECORD
