Metadata-Version: 2.4
Name: ColorfulEngine
Version: 1.0.2
Summary: Beginner-friendly library for colored terminal outputs.
Project-URL: Homepage, https://github.com/Albair581/ColorfulEngine
Project-URL: Issues, https://github.com/Albair581/ColorfulEngine/issues
Author-email: Albert Huang <albertoyucheng@gmail.com>
License-File: LICENSE
Classifier: Intended Audience :: Developers
Classifier: Intended Audience :: Education
Classifier: License :: OSI Approved :: GNU General Public License v3 (GPLv3)
Classifier: Natural Language :: Chinese (Simplified)
Classifier: Natural Language :: Chinese (Traditional)
Classifier: Natural Language :: English
Classifier: Natural Language :: Greek
Classifier: Natural Language :: Japanese
Classifier: Natural Language :: Russian
Classifier: Natural Language :: Ukrainian
Classifier: Operating System :: Microsoft :: Windows
Classifier: Programming Language :: Python :: 3
Classifier: Topic :: Education
Classifier: Topic :: Education :: Testing
Classifier: Topic :: Software Development :: Testing
Classifier: Topic :: System :: Console Fonts
Classifier: Topic :: Terminals
Requires-Python: >=3.0
Requires-Dist: colorama>=0.4.6
